proxy_checker/__init__.py
proxy_checker/proxy_checker.py
proxy_checker-0.6.dist-info/LICENSE.md
proxy_checker-0.6.dist-info/METADATA
proxy_checker-0.6.dist-info/WHEEL
proxy_checker-0.6.dist-info/top_level.txt
proxy_checker-0.6.dist-info/RECORD
