Metadata-Version: 2.1
Name: proxy_checker
Version: 0.6
Summary: Proxy checker in Python
Home-page: UNKNOWN
Author: ricerati
License: UNKNOWN
Project-URL: Source Code, https://github.com/ricerati/proxy-checker-python
Keywords: proxy checker
Platform: UNKNOWN
Classifier: License :: OSI Approved :: MIT License
